{
  "timestamp": "2026-07-10 21:51:40 UTC",
  "days_held": "13.3619",
  "spot": "63959.9",
  "entry_spot": "61242.39",
  "spot_move_pct": "4.437",
  "entry_price_btc": "0.0033",
  "current_price_btc": "0.0006",
  "current_ask_btc": "0.0007",
  "current_bid_btc": "0.0005",
  "entry_iv_pct": "55.19",
  "current_iv_pct": "56.06",
  "pnl_option_usd": "662.03",
  "pnl_hedge_usd": "-1912.41",
  "total_pnl_usd": "-1233.71",
  "pnl_pct_of_premium": "81.01",
  "tte_days": "20.4225",
  "live_delta": "-0.08964",
  "live_gamma": "2.6e-05",
  "live_vega": "21.6234",
  "hedge_qty": "-0.07898",
  "hedge_vwap": "60739.48",
  "hedge_delta_drift": "-0.34853",
  "hedge_threshold_pct": "4.47",
  "hedge_threshold_btc": "0.04475",
  "theta_daily_now_usd": "32.39",
  "theta_theory_usd": "801.02",
  "vrp_capture_pct": "82.6"
}