{
  "timestamp": "2026-06-20 00:01:07 UTC",
  "days_held": "10.9392",
  "spot": "63526.15",
  "entry_spot": "62627.18",
  "spot_move_pct": "1.435",
  "entry_price_btc": "0.005",
  "current_price_btc": "0.0037",
  "current_ask_btc": "0.0039",
  "current_bid_btc": "0.0035",
  "entry_iv_pct": "57.42",
  "current_iv_pct": "57.3",
  "pnl_option_usd": "402.63",
  "pnl_hedge_usd": "-1541.27",
  "total_pnl_usd": "-1138.64",
  "pnl_pct_of_premium": "24.94",
  "tte_days": "20.3326",
  "live_delta": "-0.08755",
  "live_gamma": "3.86e-05",
  "live_vega": "17.745",
  "hedge_qty": "-0.09607",
  "hedge_delta_drift": "-0.00852",
  "hedge_threshold_pct": "4.52",
  "hedge_threshold_btc": "0.04524",
  "theta_daily_now_usd": "51.09",
  "theta_theory_usd": "394.69",
  "vrp_capture_pct": "102.0"
}