[
  {
    "instrument": "BTC-31JUL26-48000-P",
    "tte_days": 7.7065,
    "days_held": 21.1244,
    "entry_spot": 61242.39,
    "entry_price_btc": 0.0033,
    "current_price_btc": 0.0001,
    "current_ask_btc": 0.0002,
    "current_bid_btc": 0.0001,
    "current_iv_pct": 79.81,
    "entry_iv_pct": 55.19,
    "iv_change": 24.62,
    "pnl_option_btc": 0.000905,
    "pnl_option_usd": 58.68,
    "pnl_pct_of_premium": 96.79,
    "theta_theory_usd": 104.39,
    "theta_daily_now_usd": 1.7,
    "vrp_capture_pct": 56.2,
    "live_delta": -0.00117,
    "live_gamma": 0.0,
    "live_vega": 0.3284
  },
  {
    "instrument": "BTC-24JUL26-50000-P",
    "tte_days": 0.7065,
    "days_held": 20.9972,
    "entry_spot": 61459.48,
    "entry_price_btc": 0.0026,
    "current_price_btc": 0.0,
    "current_ask_btc": 0.0001,
    "current_bid_btc": 0.0,
    "current_iv_pct": 81.8,
    "entry_iv_pct": 52.79,
    "iv_change": 29.01,
    "pnl_option_btc": 0.000246,
    "pnl_option_usd": 15.98,
    "pnl_pct_of_premium": 100.0,
    "theta_theory_usd": 39.21,
    "theta_daily_now_usd": 0.0,
    "vrp_capture_pct": 40.8,
    "live_delta": 0.0,
    "live_gamma": 0.0,
    "live_vega": 0.0
  },
  {
    "instrument": "BTC-24JUL26-54000-P",
    "tte_days": 0.7065,
    "days_held": 18.2274,
    "entry_spot": 62678.02,
    "entry_price_btc": 0.0042,
    "current_price_btc": 0.0,
    "current_ask_btc": 0.0001,
    "current_bid_btc": 0.0,
    "current_iv_pct": 81.8,
    "entry_iv_pct": 48.83,
    "iv_change": 32.97,
    "pnl_option_btc": 0.000812,
    "pnl_option_usd": 52.65,
    "pnl_pct_of_premium": 100.0,
    "theta_theory_usd": 102.95,
    "theta_daily_now_usd": 0.0,
    "vrp_capture_pct": 51.1,
    "live_delta": 0.0,
    "live_gamma": 0.0,
    "live_vega": 0.0
  },
  {
    "instrument": "BTC-31JUL26-50000-P",
    "tte_days": 7.7065,
    "days_held": 15.2043,
    "entry_spot": 61862.84,
    "entry_price_btc": 0.003,
    "current_price_btc": 0.0001,
    "current_ask_btc": 0.0002,
    "current_bid_btc": 0.0001,
    "current_iv_pct": 69.99,
    "entry_iv_pct": 54.36,
    "iv_change": 15.63,
    "pnl_option_btc": 0.000552,
    "pnl_option_usd": 35.82,
    "pnl_pct_of_premium": 96.51,
    "theta_theory_usd": 58.22,
    "theta_daily_now_usd": 1.11,
    "vrp_capture_pct": 61.5,
    "live_delta": -0.00089,
    "live_gamma": 0.0,
    "live_vega": 0.2454
  },
  {
    "instrument": "BTC-31JUL26-52000-P",
    "tte_days": 7.7065,
    "days_held": 14.1781,
    "entry_spot": 62804.63,
    "entry_price_btc": 0.003,
    "current_price_btc": 0.0002,
    "current_ask_btc": 0.0003,
    "current_bid_btc": 0.0002,
    "current_iv_pct": 64.38,
    "entry_iv_pct": 50.56,
    "iv_change": 13.82,
    "pnl_option_btc": 0.000541,
    "pnl_option_usd": 35.09,
    "pnl_pct_of_premium": 93.12,
    "theta_theory_usd": 58.01,
    "theta_daily_now_usd": 1.7,
    "vrp_capture_pct": 60.5,
    "live_delta": -0.00157,
    "live_gamma": 0.0,
    "live_vega": 0.4058
  },
  {
    "instrument": "BTC-31JUL26-58000-P",
    "tte_days": 7.7065,
    "days_held": 13.1994,
    "entry_spot": 64255.9,
    "entry_price_btc": 0.007,
    "current_price_btc": 0.0013,
    "current_ask_btc": 0.0014,
    "current_bid_btc": 0.0011,
    "current_iv_pct": 46.56,
    "entry_iv_pct": 41.22,
    "iv_change": 5.34,
    "pnl_option_btc": 0.001127,
    "pnl_option_usd": 73.1,
    "pnl_pct_of_premium": 81.26,
    "theta_theory_usd": 91.31,
    "theta_daily_now_usd": 5.39,
    "vrp_capture_pct": 80.1,
    "live_delta": -0.00897,
    "live_gamma": 4e-06,
    "live_vega": 1.7836
  },
  {
    "instrument": "BTC-24JUL26-60000-P",
    "tte_days": 0.7065,
    "days_held": 12.9495,
    "entry_spot": 64016.36,
    "entry_price_btc": 0.007,
    "current_price_btc": 0.0001,
    "current_ask_btc": 0.0001,
    "current_bid_btc": 0.0001,
    "current_iv_pct": 70.59,
    "entry_iv_pct": 37.57,
    "iv_change": 33.02,
    "pnl_option_btc": 0.001362,
    "pnl_option_usd": 88.33,
    "pnl_pct_of_premium": 98.55,
    "theta_theory_usd": 115.49,
    "theta_daily_now_usd": 0.77,
    "vrp_capture_pct": 76.5,
    "live_delta": -0.00117,
    "live_gamma": 2e-06,
    "live_vega": 0.095
  },
  {
    "instrument": "BTC-31JUL26-55000-P",
    "tte_days": 7.7065,
    "days_held": 11.2148,
    "entry_spot": 63939.96,
    "entry_price_btc": 0.0028,
    "current_price_btc": 0.0005,
    "current_ask_btc": 0.0005,
    "current_bid_btc": 0.0004,
    "current_iv_pct": 54.24,
    "entry_iv_pct": 44.72,
    "iv_change": 9.52,
    "pnl_option_btc": 0.000904,
    "pnl_option_usd": 58.64,
    "pnl_pct_of_premium": 81.89,
    "theta_theory_usd": 98.36,
    "theta_daily_now_usd": 5.35,
    "vrp_capture_pct": 59.6,
    "live_delta": -0.00646,
    "live_gamma": 4e-06,
    "live_vega": 1.5215
  },
  {
    "instrument": "BTC-31JUL26-56000-P",
    "tte_days": 7.7065,
    "days_held": 11.1646,
    "entry_spot": 63867.79,
    "entry_price_btc": 0.0039,
    "current_price_btc": 0.0006,
    "current_ask_btc": 0.0007,
    "current_bid_btc": 0.0005,
    "current_iv_pct": 51.07,
    "entry_iv_pct": 43.79,
    "iv_change": 7.28,
    "pnl_option_btc": 0.001297,
    "pnl_option_usd": 84.07,
    "pnl_pct_of_premium": 84.38,
    "theta_theory_usd": 114.01,
    "theta_daily_now_usd": 6.41,
    "vrp_capture_pct": 73.7,
    "live_delta": -0.00856,
    "live_gamma": 4e-06,
    "live_vega": 1.9334
  },
  {
    "instrument": "BTC-31JUL26-58000-P",
    "tte_days": 7.7065,
    "days_held": 11.0872,
    "entry_spot": 63998.59,
    "entry_price_btc": 0.006,
    "current_price_btc": 0.0013,
    "current_ask_btc": 0.0014,
    "current_bid_btc": 0.0011,
    "current_iv_pct": 46.56,
    "entry_iv_pct": 40.17,
    "iv_change": 6.39,
    "pnl_option_btc": 0.001387,
    "pnl_option_usd": 89.91,
    "pnl_pct_of_premium": 78.05,
    "theta_theory_usd": 112.42,
    "theta_daily_now_usd": 8.08,
    "vrp_capture_pct": 80.0,
    "live_delta": -0.01346,
    "live_gamma": 6e-06,
    "live_vega": 2.6754
  },
  {
    "instrument": "BTC-24JUL26-58000-P",
    "tte_days": 0.7065,
    "days_held": 11.0235,
    "entry_spot": 63954.36,
    "entry_price_btc": 0.0028,
    "current_price_btc": 0.0,
    "current_ask_btc": 0.0001,
    "current_bid_btc": 0.0,
    "current_iv_pct": 81.8,
    "entry_iv_pct": 40.61,
    "iv_change": 41.19,
    "pnl_option_btc": 0.000829,
    "pnl_option_usd": 53.72,
    "pnl_pct_of_premium": 100.0,
    "theta_theory_usd": 104.18,
    "theta_daily_now_usd": 0.17,
    "vrp_capture_pct": 51.6,
    "live_delta": -0.00027,
    "live_gamma": 0.0,
    "live_vega": 0.0261
  },
  {
    "instrument": "BTC-7AUG26-53000-P",
    "tte_days": 14.7065,
    "days_held": 6.2184,
    "entry_spot": 63001.57,
    "entry_price_btc": 0.0025,
    "current_price_btc": 0.0011,
    "current_ask_btc": 0.0012,
    "current_bid_btc": 0.001,
    "current_iv_pct": 53.65,
    "entry_iv_pct": 46.31,
    "iv_change": 7.34,
    "pnl_option_btc": 0.000266,
    "pnl_option_usd": 17.24,
    "pnl_pct_of_premium": 54.72,
    "theta_theory_usd": 23.05,
    "theta_daily_now_usd": 2.87,
    "vrp_capture_pct": 74.8,
    "live_delta": -0.0052,
    "live_gamma": 2e-06,
    "live_vega": 1.5748
  }
]