{
  "ts": "2026-06-19 22:45:35 UTC",
  "market_context": {
    "spot": 63245.13,
    "hv_10d": 31.34,
    "hv_30d": 41.47,
    "hv_blend": 36.41,
    "hv_1d_chg": -1.6,
    "iv_rank": 0.413,
    "iv_hv_ratio": 1.115,
    "curr_iv": 40.61,
    "dvol_1d_chg": -1.86,
    "regime": "NORMAL",
    "signal_ok": true,
    "risk_off": false,
    "cb_reduced": true,
    "cb_move_3d": -3.63,
    "cb_move_1d": 0.56,
    "cb_dvol_3d": 2.94,
    "cb_hv_5d": 33.86
  },
  "top7": [
    {
      "instrument_name": "BTC-10JUL26-52000-P",
      "strike": 52000.0,
      "expiry_ts": 1783670400000,
      "expiry_dt": "2026-07-10 08:00:00+00:00",
      "tte_days": 20.39,
      "delta": -0.06305,
      "gamma": 1e-05,
      "vega": 18.53452,
      "theta": -25.95198,
      "mark_iv": 57.09,
      "bid_iv": 56.41,
      "mark_price": 0.0039,
      "bid_price": 0.0037,
      "ask_price": 0.0041,
      "open_interest": 29.7,
      "moneyness": -17.8,
      "ba_pct": 10.3,
      "premium_usd": 234.01,
      "gamma_pts": 0.63,
      "gamma_factor": 1.0,
      "yield_ann_pct": 6.6,
      "atm_iv": 37.8,
      "skew_pct": 49.2,
      "z_score": 2.07,
      "score": 0.593,
      "score_raw": 0.593,
      "s_iv_hv": 0.366,
      "s_skew": 0.821,
      "s_rank": 0.413,
      "s_yield": 0.457,
      "iv_hv_ratio": 1.549,
      "status": "held",
      "held_entry_score": 0.621
    },
    {
      "instrument_name": "BTC-26JUN26-58000-P",
      "strike": 58000.0,
      "expiry_ts": 1782460800000,
      "expiry_dt": "2026-06-26 08:00:00+00:00",
      "tte_days": 6.39,
      "delta": -0.09001,
      "gamma": 4e-05,
      "vega": 13.59214,
      "theta": -53.58415,
      "mark_iv": 50.35,
      "bid_iv": 49.61,
      "mark_price": 0.0029,
      "bid_price": 0.0027,
      "ask_price": 0.003,
      "open_interest": 2392.5,
      "moneyness": -8.3,
      "ba_pct": 10.3,
      "premium_usd": 170.76,
      "gamma_pts": 2.53,
      "gamma_factor": 1.0,
      "yield_ann_pct": 15.4,
      "atm_iv": 36.0,
      "skew_pct": 37.9,
      "z_score": 1.72,
      "score": 0.578,
      "score_raw": 0.578,
      "s_iv_hv": 0.242,
      "s_skew": 0.631,
      "s_rank": 0.413,
      "s_yield": 0.886,
      "iv_hv_ratio": 1.363,
      "status": "held",
      "held_entry_score": 0.561
    },
    {
      "instrument_name": "BTC-3JUL26-55000-P",
      "strike": 55000.0,
      "expiry_ts": 1783065600000,
      "expiry_dt": "2026-07-03 08:00:00+00:00",
      "tte_days": 13.39,
      "delta": -0.07988,
      "gamma": 2e-05,
      "vega": 18.00789,
      "theta": -36.57495,
      "mark_iv": 54.37,
      "bid_iv": 53.9,
      "mark_price": 0.0039,
      "bid_price": 0.0038,
      "ask_price": 0.0041,
      "open_interest": 585.1,
      "moneyness": -13.0,
      "ba_pct": 7.7,
      "premium_usd": 240.33,
      "gamma_pts": 1.26,
      "gamma_factor": 1.0,
      "yield_ann_pct": 10.4,
      "atm_iv": 37.8,
      "skew_pct": 42.5,
      "z_score": 1.86,
      "score": 0.576,
      "score_raw": 0.576,
      "s_iv_hv": 0.32,
      "s_skew": 0.709,
      "s_rank": 0.413,
      "s_yield": 0.644,
      "iv_hv_ratio": 1.48,
      "status": "held",
      "held_entry_score": 0.552
    },
    {
      "instrument_name": "BTC-26JUN26-59000-P",
      "strike": 59000.0,
      "expiry_ts": 1782460800000,
      "expiry_dt": "2026-06-26 08:00:00+00:00",
      "tte_days": 6.39,
      "delta": -0.12297,
      "gamma": 5e-05,
      "vega": 17.03241,
      "theta": -62.47486,
      "mark_iv": 46.84,
      "bid_iv": 46.57,
      "mark_price": 0.0039,
      "bid_price": 0.0038,
      "ask_price": 0.0041,
      "open_interest": 1861.5,
      "moneyness": -6.7,
      "ba_pct": 7.7,
      "premium_usd": 240.33,
      "gamma_pts": 3.16,
      "gamma_factor": 1.0,
      "yield_ann_pct": 21.7,
      "atm_iv": 36.0,
      "skew_pct": 29.4,
      "z_score": 1.39,
      "score": 0.527,
      "score_raw": 0.527,
      "s_iv_hv": 0.186,
      "s_skew": 0.491,
      "s_rank": 0.413,
      "s_yield": 1.0,
      "iv_hv_ratio": 1.279,
      "status": "filtered",
      "held_entry_score": NaN
    },
    {
      "instrument_name": "BTC-3JUL26-56000-P",
      "strike": 56000.0,
      "expiry_ts": 1783065600000,
      "expiry_dt": "2026-07-03 08:00:00+00:00",
      "tte_days": 13.39,
      "delta": -0.1,
      "gamma": 3e-05,
      "vega": 21.28335,
      "theta": -41.44362,
      "mark_iv": 52.13,
      "bid_iv": 51.13,
      "mark_price": 0.0049,
      "bid_price": 0.0046,
      "ask_price": 0.005,
      "open_interest": 223.2,
      "moneyness": -11.5,
      "ba_pct": 8.2,
      "premium_usd": 290.93,
      "gamma_pts": 1.9,
      "gamma_factor": 1.0,
      "yield_ann_pct": 12.5,
      "atm_iv": 37.8,
      "skew_pct": 35.2,
      "z_score": 1.65,
      "score": 0.517,
      "score_raw": 0.517,
      "s_iv_hv": 0.27,
      "s_skew": 0.587,
      "s_rank": 0.413,
      "s_yield": 0.689,
      "iv_hv_ratio": 1.404,
      "status": "filtered",
      "held_entry_score": NaN
    },
    {
      "instrument_name": "BTC-10JUL26-54000-P",
      "strike": 54000.0,
      "expiry_ts": 1783670400000,
      "expiry_dt": "2026-07-10 08:00:00+00:00",
      "tte_days": 20.39,
      "delta": -0.08937,
      "gamma": 2e-05,
      "vega": 24.18145,
      "theta": -31.22178,
      "mark_iv": 52.64,
      "bid_iv": 51.52,
      "mark_price": 0.0054,
      "bid_price": 0.005,
      "ask_price": 0.006,
      "open_interest": 40.8,
      "moneyness": -14.6,
      "ba_pct": 18.5,
      "premium_usd": 316.23,
      "gamma_pts": 1.26,
      "gamma_factor": 1.0,
      "yield_ann_pct": 9.0,
      "atm_iv": 37.8,
      "skew_pct": 36.3,
      "z_score": 1.7,
      "score": 0.482,
      "score_raw": 0.482,
      "s_iv_hv": 0.277,
      "s_skew": 0.605,
      "s_rank": 0.413,
      "s_yield": 0.506,
      "iv_hv_ratio": 1.415,
      "status": "filtered",
      "held_entry_score": NaN
    },
    {
      "instrument_name": "BTC-10JUL26-55000-P",
      "strike": 55000.0,
      "expiry_ts": 1783670400000,
      "expiry_dt": "2026-07-10 08:00:00+00:00",
      "tte_days": 20.39,
      "delta": -0.10691,
      "gamma": 2e-05,
      "vega": 27.57602,
      "theta": -34.14278,
      "mark_iv": 50.48,
      "bid_iv": 49.45,
      "mark_price": 0.0064,
      "bid_price": 0.006,
      "ask_price": 0.007,
      "open_interest": 510.2,
      "moneyness": -13.0,
      "ba_pct": 15.6,
      "premium_usd": 379.47,
      "gamma_pts": 1.26,
      "gamma_factor": 1.0,
      "yield_ann_pct": 10.7,
      "atm_iv": 37.8,
      "skew_pct": 30.8,
      "z_score": 1.51,
      "score": 0.438,
      "score_raw": 0.438,
      "s_iv_hv": 0.239,
      "s_skew": 0.514,
      "s_rank": 0.413,
      "s_yield": 0.541,
      "iv_hv_ratio": 1.358,
      "status": "filtered",
      "held_entry_score": NaN
    },
    {
      "instrument_name": "BTC-3JUL26-59000-P",
      "strike": 59000.0,
      "expiry_ts": 1783065600000,
      "expiry_dt": "2026-07-03 08:00:00+00:00",
      "tte_days": 13.39,
      "delta": -0.19387,
      "gamma": 5e-05,
      "vega": 33.31699,
      "theta": -56.0404,
      "mark_iv": 45.03,
      "bid_iv": 44.76,
      "mark_price": 0.0096,
      "bid_price": 0.0095,
      "ask_price": 0.01,
      "open_interest": 5.3,
      "moneyness": -6.7,
      "ba_pct": 5.2,
      "premium_usd": 600.83,
      "gamma_pts": 3.16,
      "gamma_factor": 1.0,
      "yield_ann_pct": 25.9,
      "atm_iv": 37.8,
      "skew_pct": 18.4,
      "z_score": 0.96,
      "score": 0.391,
      "score_raw": 0.391,
      "s_iv_hv": 0.153,
      "s_skew": 0.306,
      "s_rank": 0.413,
      "s_yield": 0.829,
      "iv_hv_ratio": 1.229,
      "status": "eligible",
      "held_entry_score": NaN
    }
  ]
}