{
  "ts": "2026-07-19 01:47:03 UTC",
  "market_context": {
    "spot": 64727.5,
    "hv_10d": 32.06,
    "hv_30d": 26.95,
    "hv_blend": 29.51,
    "hv_1d_chg": 1.99,
    "iv_rank": 0.0,
    "iv_hv_ratio": 1.21,
    "curr_iv": 35.72,
    "dvol_1d_chg": -0.59,
    "regime": "LOW",
    "signal_ok": true,
    "risk_off": false,
    "cb_reduced": false,
    "cb_move_3d": 0.17,
    "cb_move_1d": 1.25,
    "cb_dvol_3d": -0.2,
    "cb_hv_5d": 38.99
  },
  "top7": [
    {
      "instrument_name": "BTC-31JUL26-59000-P",
      "strike": 59000.0,
      "expiry_ts": 1785484800000,
      "expiry_dt": "2026-07-31 08:00:00+00:00",
      "tte_days": 12.26,
      "delta": -0.09718,
      "gamma": 4e-05,
      "vega": 20.41251,
      "theta": -33.83742,
      "mark_iv": 40.64,
      "bid_iv": 40.27,
      "mark_price": 0.0035,
      "bid_price": 0.0034,
      "ask_price": 0.0037,
      "open_interest": 1751.8,
      "moneyness": -8.8,
      "ba_pct": 8.6,
      "premium_usd": 220.07,
      "gamma_pts": 2.59,
      "gamma_factor": 1.0,
      "yield_ann_pct": 10.1,
      "atm_iv": 33.8,
      "skew_pct": 19.0,
      "z_score": 1.63,
      "score": 0.353,
      "score_raw": 0.353,
      "s_iv_hv": 0.243,
      "s_skew": 0.317,
      "s_rank": 0.0,
      "s_yield": 0.549,
      "iv_hv_ratio": 1.365,
      "status": "filtered",
      "held_entry_score": 0.6141000000000001
    },
    {
      "instrument_name": "BTC-7AUG26-58000-P",
      "strike": 58000.0,
      "expiry_ts": 1786089600000,
      "expiry_dt": "2026-08-07 08:00:00+00:00",
      "tte_days": 19.26,
      "delta": -0.10963,
      "gamma": 3e-05,
      "vega": 27.94231,
      "theta": -29.84344,
      "mark_iv": 41.14,
      "bid_iv": 40.42,
      "mark_price": 0.0052,
      "bid_price": 0.0049,
      "ask_price": 0.0055,
      "open_interest": 106.4,
      "moneyness": -10.4,
      "ba_pct": 11.5,
      "premium_usd": 317.16,
      "gamma_pts": 1.94,
      "gamma_factor": 1.0,
      "yield_ann_pct": 9.3,
      "atm_iv": 33.6,
      "skew_pct": 20.3,
      "z_score": 1.53,
      "score": 0.345,
      "score_raw": 0.345,
      "s_iv_hv": 0.246,
      "s_skew": 0.338,
      "s_rank": 0.0,
      "s_yield": 0.475,
      "iv_hv_ratio": 1.37,
      "status": "filtered",
      "held_entry_score": 0.478
    },
    {
      "instrument_name": "BTC-31JUL26-60000-P",
      "strike": 60000.0,
      "expiry_ts": 1785484800000,
      "expiry_dt": "2026-07-31 08:00:00+00:00",
      "tte_days": 12.26,
      "delta": -0.13588,
      "gamma": 5e-05,
      "vega": 25.90256,
      "theta": -41.81255,
      "mark_iv": 39.58,
      "bid_iv": 38.69,
      "mark_price": 0.0052,
      "bid_price": 0.0048,
      "ask_price": 0.0055,
      "open_interest": 2500.9,
      "moneyness": -7.3,
      "ba_pct": 13.5,
      "premium_usd": 310.69,
      "gamma_pts": 3.24,
      "gamma_factor": 1.0,
      "yield_ann_pct": 14.3,
      "atm_iv": 33.8,
      "skew_pct": 14.3,
      "z_score": 1.35,
      "score": 0.33,
      "score_raw": 0.33,
      "s_iv_hv": 0.207,
      "s_skew": 0.239,
      "s_rank": 0.0,
      "s_yield": 0.643,
      "iv_hv_ratio": 1.311,
      "status": "filtered",
      "held_entry_score": 0.6240666666666667
    },
    {
      "instrument_name": "BTC-24JUL26-62000-P",
      "strike": 62000.0,
      "expiry_ts": 1784880000000,
      "expiry_dt": "2026-07-24 08:00:00+00:00",
      "tte_days": 5.26,
      "delta": -0.1492,
      "gamma": 8e-05,
      "vega": 18.06267,
      "theta": -61.40722,
      "mark_iv": 35.76,
      "bid_iv": 35.12,
      "mark_price": 0.0034,
      "bid_price": 0.0032,
      "ask_price": 0.0034,
      "open_interest": 160.3,
      "moneyness": -4.2,
      "ba_pct": 5.9,
      "premium_usd": 207.13,
      "gamma_pts": 5.18,
      "gamma_factor": 0.964,
      "yield_ann_pct": 22.2,
      "atm_iv": 31.7,
      "skew_pct": 10.8,
      "z_score": 1.19,
      "score": 0.326,
      "score_raw": 0.338,
      "s_iv_hv": 0.127,
      "s_skew": 0.179,
      "s_rank": 0.0,
      "s_yield": 0.878,
      "iv_hv_ratio": 1.19,
      "status": "filtered",
      "held_entry_score": 0.546
    },
    {
      "instrument_name": "BTC-7AUG26-60000-P",
      "strike": 60000.0,
      "expiry_ts": 1786089600000,
      "expiry_dt": "2026-08-07 08:00:00+00:00",
      "tte_days": 19.26,
      "delta": -0.17763,
      "gamma": 5e-05,
      "vega": 38.76256,
      "theta": -38.68169,
      "mark_iv": 38.44,
      "bid_iv": 37.87,
      "mark_price": 0.0088,
      "bid_price": 0.0085,
      "ask_price": 0.009,
      "open_interest": 45.6,
      "moneyness": -7.3,
      "ba_pct": 5.7,
      "premium_usd": 550.18,
      "gamma_pts": 3.24,
      "gamma_factor": 1.0,
      "yield_ann_pct": 16.1,
      "atm_iv": 33.6,
      "skew_pct": 12.7,
      "z_score": 1.08,
      "score": 0.297,
      "score_raw": 0.297,
      "s_iv_hv": 0.189,
      "s_skew": 0.212,
      "s_rank": 0.0,
      "s_yield": 0.578,
      "iv_hv_ratio": 1.283,
      "status": "eligible",
      "held_entry_score": NaN
    },
    {
      "instrument_name": "BTC-31JUL26-61000-P",
      "strike": 61000.0,
      "expiry_ts": 1785484800000,
      "expiry_dt": "2026-07-31 08:00:00+00:00",
      "tte_days": 12.26,
      "delta": -0.18087,
      "gamma": 6e-05,
      "vega": 31.25999,
      "theta": -48.00589,
      "mark_iv": 37.65,
      "bid_iv": 36.6,
      "mark_price": 0.007,
      "bid_price": 0.0065,
      "ask_price": 0.0075,
      "open_interest": 839.9,
      "moneyness": -5.8,
      "ba_pct": 14.3,
      "premium_usd": 420.73,
      "gamma_pts": 3.88,
      "gamma_factor": 1.0,
      "yield_ann_pct": 19.4,
      "atm_iv": 33.8,
      "skew_pct": 8.2,
      "z_score": 1.07,
      "score": 0.282,
      "score_raw": 0.282,
      "s_iv_hv": 0.16,
      "s_skew": 0.136,
      "s_rank": 0.0,
      "s_yield": 0.692,
      "iv_hv_ratio": 1.24,
      "status": "filtered",
      "held_entry_score": 0.5462
    },
    {
      "instrument_name": "BTC-31JUL26-62000-P",
      "strike": 62000.0,
      "expiry_ts": 1785484800000,
      "expiry_dt": "2026-07-31 08:00:00+00:00",
      "tte_days": 12.26,
      "delta": -0.24379,
      "gamma": 7e-05,
      "vega": 37.23797,
      "theta": -55.56471,
      "mark_iv": 36.58,
      "bid_iv": 35.7,
      "mark_price": 0.01,
      "bid_price": 0.0095,
      "ask_price": 0.0105,
      "open_interest": 1137.3,
      "moneyness": -4.2,
      "ba_pct": 10.0,
      "premium_usd": 614.91,
      "gamma_pts": 4.53,
      "gamma_factor": 1.0,
      "yield_ann_pct": 28.3,
      "atm_iv": 33.8,
      "skew_pct": 5.5,
      "z_score": 0.78,
      "score": 0.266,
      "score_raw": 0.266,
      "s_iv_hv": 0.14,
      "s_skew": 0.092,
      "s_rank": 0.0,
      "s_yield": 0.732,
      "iv_hv_ratio": 1.21,
      "status": "eligible",
      "held_entry_score": NaN
    }
  ]
}